{
  "basiselementen": {
    "font": {
      "sans-serif": {
        "font-family": {
          "value": "'RijksoverheidSansWebText'"
        }
      },
      "sans-serif-fallback": {
        "font-family": {
          "value": "'Calibri', 'Verdana', 'Arial', sans-serif"
        }
      },
      "serif": {
        "font-family": {
          "value": "'RijksoverheidSerifWeb'"
        }
      },
      "serif-fallback": {
        "font-family": {
          "value": "'Times New Roman', serif"
        }
      }
    },
    "font-weight": {
      "normal": {
        "value": "400"
      },
      "bold": {
        "value": "700"
      }
    }
  }
}
