{
  "rhc": {
    "font-size": {
      "heading": {
        "level-1": {
          "value": "{rhc.font-size.xl.tablet}",
          "type": "fontSizes"
        },
        "level-2": {
          "value": "{rhc.font-size.lg.tablet}",
          "type": "fontSizes"
        },
        "level-3": {
          "value": "{rhc.font-size.md.tablet}",
          "type": "fontSizes"
        },
        "level-4": {
          "value": "{rhc.font-size.sm.tablet}",
          "type": "fontSizes"
        },
        "level-5": {
          "value": "{rhc.font-size.xs.tablet}",
          "type": "fontSizes"
        }
      },
      "body": {
        "intro": {
          "value": "{rhc.font-size.sm.tablet}",
          "type": "fontSizes"
        },
        "default": {
          "value": "{rhc.font-size.xs.tablet}",
          "type": "fontSizes"
        }
      }
    }
  }
}